<?xml version="1.0" encoding="UTF-8"?>
<beans xmlns="http://www.springframework.org/schema/beans"
  xmlns:xsi="http://www.w3.org/2001/XMLSchema-instance"
  xmlns:tx="http://www.springframework.org/schema/tx"
  xsi:schemaLocation="http://www.springframework.org/schema/beans
    http://www.springframework.org/schema/beans/spring-beans.xsd
    http://www.springframework.org/schema/tx
    http://www.springframework.org/schema/tx/spring-tx.xsd" 
  default-autowire="byName">

  <!-- filter for core geoserver monitor extension -->
  <bean id="gsMonitorFilter" class="org.opengeo.analytics.web.GeoServerMonitorFilter"/>
  
  <bean id="analyticsMenuPage" class="org.geoserver.web.MenuPageInfo">
      <property name="id" value="category.monitor"/>
      <property name="titleKey" value="AnalyticsHomePage.title"/>
      <property name="descriptionKey" value="AnalyticsHomePage.description"/>
      <property name="componentClass" value="org.opengeo.analytics.web.AnalyticsHomePage"/>
  </bean>
   
  <bean id="analyticsRequestMapInitializer" class="org.opengeo.analytics.RequestMapInitializer">
    <constructor-arg ref="monitorDataSource"/>
  </bean>
</beans>
