<pkgref spec="1.12" uuid="ECF538B3-A02A-4556-AC02-98B1A59E1029"><config><identifier>org.opengeo.suite.oracle.pkg</identifier><version>1</version><description></description><post-install type="none"/><requireAuthorization/><installFrom relative="true" mod="true">pkg/ext/oracle</installFrom><installTo mod="true">/Applications/OpenGeo Suite.app/Contents/Resources/Java/webapps/geoserver/WEB-INF/lib</installTo><flags><followSymbolicLinks/></flags><packageStore type="internal"></packageStore><mod>parent</mod><mod>installFrom.isRelativeType</mod><mod>installTo.path</mod><mod>identifier</mod><mod>installTo</mod></config><contents><file-list>05oracle-contents.xml</file-list><filter>/CVS$</filter><filter>/\.svn$</filter><filter>/\.cvsignore$</filter><filter>/\.cvspass$</filter><filter>/\.DS_Store$</filter></contents></pkgref>